{
	"기아㈜": {
		"state": "시작",
		"content": "[경영지원] 그래픽 디자인, 홍보 영상 컨텐츠 촬영 및 편집",
		"position": "경력무관",
		"plan": "02/01~02/10",
		"link": "/Company/1646692/Info",
		"img": "https://imgs.jobkorea.co.kr/img1/_whitebg/200X80/Co_Logo/Logo/2021/1/08/2k73f00aRi_zKvylp9kv3o22i0gfYnIg_ga6w2fi.png?v=202302121613&hash=r&serviceCode=CL",
		"시작일": "2023.02.01(수)",
		"종료일": "2023.02.10(금)"
	},
	"한국조선해양": {
		"state": "시작",
		"content": "2023년도 사무지원직 신입사원 모집",
		"position": "신입",
		"plan": "02/01~02/13",
		"link": "/Company/1896740/Info",
		"img": "https://imgs.jobkorea.co.kr/img1/_whitebg/200X80/Co_Logo/Logo/2019/7/2835s008R-_4X9u6963521-0esY8U0_9-2s-.jpg?v=202302121613&hash=r&serviceCode=CL",
		"시작일": "2023.02.01(수)",
		"종료일": "2023.02.13(월)"
	},
	"현대제철주식회사": {
		"state": "시작",
		"content": "현대제철㈜ 사무행정 계약직 채용(판교)",
		"position": "경력무관",
		"plan": "02/01~02/03",
		"link": "/Company/1633016/Info",
		"img": "https://imgs.jobkorea.co.kr/img1/_whitebg/200X80/Co_Logo/Logo/2014/6/2s3cr008Ri_cXdahaf3c2gi0erYrUk_dd2ri.gif?v=202302121613&hash=r&serviceCode=CL",
		"시작일": "2023.02.01(수)",
		"종료일": "2023.02.03(금)"
	},
	"㈜E1": {
		"state": "시작",
		"content": "2023년 사업개발본부(EV팀/수소팀) 사무지원 [보훈 특별 채용]",
		"position": "경력무관",
		"plan": "02/01~02/17",
		"link": "/Company/1947200/Info",
		"img": "https://imgs.jobkorea.co.kr/img1/_whitebg/200X80/Co_Logo/Logo/2012/10/2t7ps005Rp_nK2l2t2xp0bsYpIx_sp.gif?v=202302121613&hash=r&serviceCode=CL",
		"시작일": "2023.02.01(수)",
		"종료일": "2023.02.17(금)"
	},
	"금호석유화학㈜": {
		"state": "시작",
		"content": "2023년 기술직 인턴사원 채용",
		"position": "인턴·신입",
		"plan": "02/01~02/07",
		"link": "/Company/1349835/Info",
		"img": "https://imgs.jobkorea.co.kr/img1/_whitebg/200X80/Co_Logo/Logo/2021/1/22/2437s008R-_2X7u5923720-0esY8U3_7-2s-.jpg?v=202302121613&hash=r&serviceCode=CL",
		"시작일": "2023.02.01(수)",
		"종료일": "2023.02.07(화)"
	}
}